{
   "list_of_users":[
      {
         "id":"ay2642",
         "type":"",
         "image":"https://minimaltoolkit.com/images/randomdata/male/94.jpg",
         "name":"Jorge ",
         "second_name":"Fraga Cal",
         "age":"",
         "condition":"",
         "username":"",
         "email":"jorge.fraga1997@gmail.com",
         "mobile_number":"666 666 666",
         "created_at":"",
         "update_at":"",
         "direction":"",
         "payments":[
            {
               "state":"",
               "product":"",
               "price":"",
               "day":"",
               "time":""
            }
         ],
         "bonos":"",
         "reservations":[
            {
               "day":"",
               "time":"",
               "state":""
            }
         ],
         "exercices":[
            {
               "name":"",
               "score":[
                  {
                     "date":"",
                     "weigth":""
                  }
               ]
            }
         ]
      },{
         "id":"",
         "type":"",
         "image":"https://minimaltoolkit.com/images/randomdata/male/94.jpg",
         "name":"Jorge ",
         "second_name":"Fraga Cal",
         "age":"",
         "condition":"",
         "username":"",
         "email":"jorge.fraga1997@gmail.com",
         "mobile_number":"666 666 666",
         "created_at":"",
         "update_at":"",
         "direction":"",
         "payments":[
            {
               "state":"",
               "product":"",
               "price":"",
               "day":"",
               "time":""
            }
         ],
         "bonos":"",
         "reservations":[
            {
               "day":"",
               "time":"",
               "state":""
            }
         ],
         "exercices":[
            {
               "name":"",
               "score":[
                  {
                     "date":"",
                     "weigth":""
                  }
               ]
            }
         ]
      },{
         "id":"",
         "type":"",
         "image":"https://minimaltoolkit.com/images/randomdata/male/94.jpg",
         "name":"Jorge ",
         "second_name":"Fraga Cal",
         "age":"",
         "condition":"",
         "username":"",
         "email":"jorge.fraga1997@gmail.com",
         "mobile_number":"666 666 666",
         "created_at":"",
         "update_at":"",
         "direction":"",
         "payments":[
            {
               "state":"",
               "product":"",
               "price":"",
               "day":"",
               "time":""
            }
         ],
         "bonos":"",
         "reservations":[
            {
               "day":"",
               "time":"",
               "state":""
            }
         ],
         "exercices":[
            {
               "name":"",
               "score":[
                  {
                     "date":"",
                     "weigth":""
                  }
               ]
            }
         ]
      },{
         "id":"",
         "type":"",
         "image":"https://minimaltoolkit.com/images/randomdata/male/94.jpg",
         "name":"Jorge ",
         "second_name":"Fraga Cal",
         "age":"",
         "condition":"",
         "username":"",
         "email":"jorge.fraga1997@gmail.com",
         "mobile_number":"666 666 666",
         "created_at":"",
         "update_at":"",
         "direction":"",
         "payments":[
            {
               "state":"",
               "product":"",
               "price":"",
               "day":"",
               "time":""
            }
         ],
         "bonos":"",
         "reservations":[
            {
               "day":"",
               "time":"",
               "state":""
            }
         ],
         "exercices":[
            {
               "name":"",
               "score":[
                  {
                     "date":"",
                     "weigth":""
                  }
               ]
            }
         ]
      },{
         "id":"",
         "type":"",
         "image":"https://minimaltoolkit.com/images/randomdata/male/94.jpg",
         "name":"Jorge ",
         "second_name":"Fraga Cal",
         "age":"",
         "condition":"",
         "username":"",
         "email":"jorge.fraga1997@gmail.com",
         "mobile_number":"666 666 666",
         "created_at":"",
         "update_at":"",
         "direction":"",
         "payments":[
            {
               "state":"",
               "product":"",
               "price":"",
               "day":"",
               "time":""
            }
         ],
         "bonos":"",
         "reservations":[
            {
               "day":"",
               "time":"",
               "state":""
            }
         ],
         "exercices":[
            {
               "name":"",
               "score":[
                  {
                     "date":"",
                     "weigth":""
                  }
               ]
            }
         ]
      },{
         "id":"",
         "type":"",
         "image":"https://minimaltoolkit.com/images/randomdata/male/94.jpg",
         "name":"Jorge ",
         "second_name":"Fraga Cal",
         "age":"",
         "condition":"",
         "username":"",
         "email":"jorge.fraga1997@gmail.com",
         "mobile_number":"666 666 666",
         "created_at":"",
         "update_at":"",
         "direction":"",
         "payments":[
            {
               "state":"",
               "product":"",
               "price":"",
               "day":"",
               "time":""
            }
         ],
         "bonos":"",
         "reservations":[
            {
               "day":"",
               "time":"",
               "state":""
            }
         ],
         "exercices":[
            {
               "name":"",
               "score":[
                  {
                     "date":"",
                     "weigth":""
                  }
               ]
            }
         ]
      },{
         "id":"",
         "type":"",
         "image":"https://minimaltoolkit.com/images/randomdata/male/94.jpg",
         "name":"Jorge ",
         "second_name":"Fraga Cal",
         "age":"",
         "condition":"",
         "username":"",
         "email":"jorge.fraga1997@gmail.com",
         "mobile_number":"666 666 666",
         "created_at":"",
         "update_at":"",
         "direction":"",
         "payments":[
            {
               "state":"",
               "product":"",
               "price":"",
               "day":"",
               "time":""
            }
         ],
         "bonos":"",
         "reservations":[
            {
               "day":"",
               "time":"",
               "state":""
            }
         ],
         "exercices":[
            {
               "name":"",
               "score":[
                  {
                     "date":"",
                     "weigth":""
                  }
               ]
            }
         ]
      }
   ]
}
