{
   "exercise_list":[
      {
         "name":"Front Squat",
         "image":"",
         "category":""
      },
      {
         "name":"Ring Push-Up",
         "image":"",
         "category":""
      },
      {
         "name":"Kipping Handstand Push-up",
         "image":"",
         "category":""
      },
      {
         "name":"Clean and Push Jerk",
         "image":"",
         "category":""
      },
      {
         "name":"Rope Climb (Basket)",
         "image":"",
         "category":""
      },
      {
         "name":"Power Clean and Split Jerk",
         "image":"",
         "category":""
      },
      {
         "name":"Toes-to-Bar",
         "image":"",
         "category":""
      },
      {
         "name":"Hang Clean and Push Jerk",
         "image":"",
         "category":""
      },
      {
         "name":"Muscle Snatch",
         "image":"",
         "category":""
      },
      {
         "name":"Hang Power Clean and Push Jerk",
         "image":"",
         "category":""
      },
      {
         "name":"Kipping Toes-to-Bar",
         "image":"",
         "category":""
      },
      {
         "name":"Dumbbell Power Snatch",
         "image":"",
         "category":""
      },
      {
         "name":"Chest-to-Wall Handstand Push-Up",
         "image":"",
         "category":""
      },
      {
         "name":"Burpee",
         "image":"",
         "category":""
      },
      {
         "name":"Dumbbell Push Press",
         "image":"",
         "category":""
      },
      {
         "name":"Dumbbell Power Clean",
         "image":"",
         "category":""
      },
      {
         "name":"Freestanding Handstand Push-Up",
         "image":"",
         "category":""
      },
      {
         "name":"Sots Press",
         "image":"",
         "category":""
      },
      {
         "name":"Muscle-Up",
         "image":"",
         "category":""
      },
      {
         "name":"Kipping Deficit Handstand Push-Up",
         "image":"",
         "category":""
      },
      {
         "name":"Dumbbell Clean",
         "image":"",
         "category":""
      },
      {
         "name":"Clean and Jerk",
         "image":"",
         "category":""
      },
      {
         "name":"Hanging L-Sit",
         "image":"",
         "category":""
      },
      {
         "name":"Pull-Up",
         "image":"",
         "category":""
      },
      {
         "name":"Ring Dip",
         "image":"",
         "category":""
      },
      {
         "name":"Hang Snatch",
         "image":"",
         "category":""
      },
      {
         "name":"Split Clean",
         "image":"",
         "category":""
      },
      {
         "name":"Box Step-Up",
         "image":"",
         "category":""
      },
      {
         "name":"Dumbbell Front Squat",
         "image":"",
         "category":""
      },
      {
         "name":"Hang Clean",
         "image":"",
         "category":""
      },
      {
         "name":"Dumbbell Push Jerk",
         "image":"",
         "category":""
      },
      {
         "name":"Dip",
         "image":"",
         "category":""
      },
      {
         "name":"Dumbbell Deadlift",
         "image":"",
         "category":""
      },
      {
         "name":"Split Snatch",
         "image":"",
         "category":""
      },
      {
         "name":"Pull-Over",
         "image":"",
         "category":""
      },
      {
         "name":"Sumo Deadlift",
         "image":"",
         "category":""
      },
      {
         "name":"Kettlebell Swing",
         "image":"",
         "category":""
      },
      {
         "name":"Air Squat",
         "image":"",
         "category":""
      },
      {
         "name":"Split Jerk",
         "image":"",
         "category":""
      },
      {
         "name":"Kettlebell Snatch",
         "image":"",
         "category":""
      },
      {
         "name":"Wall Walk",
         "image":"",
         "category":""
      },
      {
         "name":"Hang Power Snatch",
         "image":"",
         "category":""
      },
      {
         "name":"Dumbbell Thruster",
         "image":"",
         "category":""
      },
      {
         "name":"Kipping Muscle-Up",
         "image":"",
         "category":""
      },
      {
         "name":"Dumbbell Hang Clean",
         "image":"",
         "category":""
      },
      {
         "name":"Hang Power Clean",
         "image":"",
         "category":""
      },
      {
         "name":"Box Jump",
         "image":"",
         "category":""
      },
      {
         "name":"AbMat Sit-Up",
         "image":"",
         "category":""
      },
      {
         "name":"Deadlift",
         "image":"",
         "category":""
      },
      {
         "name":"Power Snatch",
         "image":"",
         "category":""
      },
      {
         "name":"Clean",
         "image":"",
         "category":""
      },
      {
         "name":"Snatch",
         "image":"",
         "category":""
      },
      {
         "name":"Dumbbell Overhead Squat",
         "image":"",
         "category":""
      },
      {
         "name":"GHD Sit-Up",
         "image":"",
         "category":""
      },
      {
         "name":"Wall-Ball Shot",
         "image":"",
         "category":""
      },
      {
         "name":"Ring Row",
         "image":"",
         "category":""
      },
      {
         "name":"Kipping Pull-Up",
         "image":"",
         "category":""
      },
      {
         "name":"Clean & Jerk",
         "image":"",
         "category":""
      },
      {
         "name":"Clean",
         "image":"",
         "category":""
      },
      {
         "name":"Single-Leg Squat",
         "image":"",
         "category":""
      },
      {
         "name":"Dumbbell Squat Snatch",
         "image":"",
         "category":""
      },
      {
         "name":"Dumbbell Farmers Carry",
         "image":"",
         "category":""
      }
   ]
}
